sllmipy/__init__.py
sllmipy/base_llm_model.py
sllmipy/gemini.py
sllmipy/llms.py
sllmipy/models.py
sllmipy-0.3.3.dist-info/METADATA
sllmipy-0.3.3.dist-info/WHEEL
sllmipy-0.3.3.dist-info/top_level.txt
sllmipy-0.3.3.dist-info/RECORD
