Metadata-Version: 2.4
Name: sllmipy
Version: 0.3.3
Summary: simple llm interface for python
Requires-Python: >=3.9
Requires-Dist: pydantic
Requires-Dist: google-genai
Requires-Dist: google-cloud-aiplatform[tokenization]
